vee_qa/__init__.py
vee_qa/matched_qa.py
vee_qa/quality_assessments.py
vaynerqualityassessments-0.1.21.dist-info/METADATA
vaynerqualityassessments-0.1.21.dist-info/WHEEL
vaynerqualityassessments-0.1.21.dist-info/top_level.txt
vaynerqualityassessments-0.1.21.dist-info/RECORD
