Metadata-Version: 2.1
Name: vaynerqualityassessments
Version: 0.1.21
Summary: Quality assessment functions for Tracer Data
Home-page: 
Author: Will Butler
Author-email: will.butler@vaynermedia.com
License: MIT
Platform: UNKNOWN
Classifier: Intended Audience :: Developers
Classifier: License :: OSI Approved :: MIT License
Classifier: Programming Language :: Python
Classifier: Programming Language :: Python :: 3
Classifier: Programming Language :: Python :: 3.6
Classifier: Programming Language :: Python :: 3.7
Classifier: Programming Language :: Python :: 3.8
Classifier: Programming Language :: Python :: 3.9
Classifier: Operating System :: OS Independent
Requires-Dist: numpy
Requires-Dist: pandas
Requires-Dist: regex
Requires-Dist: datetime
Requires-Dist: veetility
